setup.py
TemplateTemplate.egg-info/PKG-INFO
TemplateTemplate.egg-info/SOURCES.txt
TemplateTemplate.egg-info/dependency_links.txt
TemplateTemplate.egg-info/entry_points.txt
TemplateTemplate.egg-info/not-zip-safe
TemplateTemplate.egg-info/requires.txt
TemplateTemplate.egg-info/top_level.txt
templatetemplate/__init__.py
templatetemplate/template/setup.py_tmpl
templatetemplate/template/+package+/__init__.py_tmpl
templatetemplate/template/+package+/template/README.txt_tmpl