Metadata-Version: 1.0
Name: TemplateTemplate
Version: 0.1
Summary: paste template for a paste template
Home-page: UNKNOWN
Author: Jeff Hammel
Author-email: jhammel@openplans.org
License: GPL
Keywords: template
Platform: UNKNOWN
